{
  "publicPath": "/_nuxt/",
  "all": [
    "../server/index.spa.html",
    "../server/index.ssr.html",
    "0d6d1e0.js",
    "1c89a98.js",
    "21b145b.js",
    "404dfba.js",
    "41ef2dc.js",
    "47366b6.js",
    "8cafa7b.js",
    "8da1490.js",
    "LICENSES",
    "bb01b66.js",
    "cf78498.js"
  ],
  "initial": [
    "1c89a98.js",
    "cf78498.js",
    "8da1490.js",
    "0d6d1e0.js"
  ],
  "async": [
    "21b145b.js",
    "404dfba.js",
    "41ef2dc.js",
    "47366b6.js",
    "8cafa7b.js",
    "bb01b66.js"
  ],
  "modules": {
    "14211200": [
      9
    ],
    "18417528": [
      4
    ],
    "28851446": [
      11,
      7
    ],
    "34150012": [
      7
    ],
    "38042737": [
      8
    ],
    "38981327": [
      12
    ],
    "54066724": [
      12
    ],
    "66406444": [
      12
    ],
    "70522606": [
      2
    ],
    "72474304": [
      7
    ],
    "16168cae": [
      2
    ],
    "41858a19": [
      12
    ],
    "c3237696": [
      12
    ],
    "c73ecb34": [
      12
    ],
    "0b8c4790": [
      12
    ],
    "6f7a5a24": [
      12
    ],
    "a0148b2c": [
      12
    ],
    "07c32b22": [
      12
    ],
    "9cf166f4": [
      12
    ],
    "261c7f42": [
      12
    ],
    "7541e0e1": [
      12
    ],
    "6f0a189d": [
      12
    ],
    "bc8218dc": [
      12
    ],
    "80988e28": [
      12
    ],
    "0971d114": [
      12
    ],
    "50e8157a": [
      12
    ],
    "78fd192a": [
      12
    ],
    "12e13280": [
      12
    ],
    "c3e9980a": [
      12
    ],
    "2b5e384d": [
      12
    ],
    "729374da": [
      12
    ],
    "aa70a1a0": [
      12
    ],
    "d7a690f8": [
      12
    ],
    "bda5a422": [
      12
    ],
    "163dfb78": [
      12
    ],
    "4f65abcf": [
      12
    ],
    "4ec97558": [
      12
    ],
    "43b568ce": [
      12
    ],
    "0bb73fc4": [
      12
    ],
    "2fcf3bad": [
      12
    ],
    "7f65c22e": [
      12
    ],
    "83ded1a4": [
      12
    ],
    "253be1aa": [
      12
    ],
    "fc4e0c70": [
      12
    ],
    "1d8b1626": [
      2
    ],
    "618b14b4": [
      2
    ],
    "76ca4ca2": [
      2
    ],
    "9bf205ba": [
      2
    ],
    "c9d20944": [
      2
    ],
    "1c391f33": [
      2
    ],
    "1ce2192f": [
      2
    ],
    "d1319a0a": [
      2
    ],
    "f894c950": [
      2
    ],
    "12fbdbd6": [
      2
    ],
    "63c0a956": [
      2
    ],
    "70177e46": [
      2
    ],
    "1b58c694": [
      2
    ],
    "7327fc4a": [
      2
    ],
    "72f8c300": [
      2
    ],
    "f9882d76": [
      2
    ],
    "74a6fe3c": [
      2
    ],
    "6d52c6cd": [
      2
    ],
    "261eee91": [
      2
    ],
    "570c47f5": [
      2
    ],
    "4e4c42c8": [
      12
    ],
    "743b07b7": [
      12
    ],
    "210ead6e": [
      12
    ],
    "7ab940e0": [
      12
    ],
    "1fce05a7": [
      12
    ],
    "ac780e92": [
      12
    ],
    "702fcdf3": [
      12
    ],
    "6d3e394e": [
      12
    ],
    "c9d45c9e": [
      12
    ],
    "5e09f380": [
      12
    ],
    "408e5e35": [
      12
    ],
    "60d52806": [
      12
    ],
    "7a635d64": [
      12
    ],
    "df6aa254": [
      12
    ],
    "a6cd7d18": [
      12
    ],
    "c2a8ce78": [
      12
    ],
    "6f8db5a4": [
      12
    ],
    "cd17b7da": [
      12
    ],
    "d795114a": [
      12
    ],
    "ed988706": [
      12
    ],
    "53f2eb3b": [
      12
    ],
    "bb871d40": [
      12
    ],
    "187f2a14": [
      9
    ],
    "62e62e27": [
      12
    ],
    "4b15682f": [
      9
    ],
    "305c123c": [
      12
    ],
    "03ffba52": [
      12
    ],
    "08ae68fd": [
      12
    ],
    "04857bd2": [
      12
    ],
    "5c4918c5": [
      12
    ],
    "0e68af65": [
      12
    ],
    "12807d96": [
      12
    ],
    "c301a402": [
      12
    ],
    "a267fd14": [
      12
    ],
    "31f48f5e": [
      12
    ],
    "544f39e0": [
      12
    ],
    "34b98b43": [
      12
    ],
    "9a131f1c": [
      12
    ],
    "7b4e5d7a": [
      12
    ],
    "22c864fe": [
      12
    ],
    "5a354770": [
      12
    ],
    "00288c7f": [
      9
    ],
    "e4941c62": [
      9
    ],
    "b87a0294": [
      9
    ],
    "751f0e84": [
      12
    ],
    "1f2de56e": [
      12
    ],
    "835fe7a8": [
      12
    ],
    "3c039fcd": [
      12
    ],
    "26fc2264": [
      12
    ],
    "3bf2f608": [
      12
    ],
    "d3662716": [
      12
    ],
    "0c4540dc": [
      12
    ],
    "3927eaae": [
      12
    ],
    "4cce4eae": [
      12
    ],
    "65764e9a": [
      12
    ],
    "27edb09c": [
      12
    ],
    "05a95cfc": [
      12
    ],
    "1eda648b": [
      12
    ],
    "29a12b50": [
      12
    ],
    "e23178ba": [
      12
    ],
    "3251530f": [
      12
    ],
    "5a52c403": [
      9
    ],
    "2cdac42a": [
      12
    ],
    "11024c3d": [
      12
    ],
    "510124a4": [
      12
    ],
    "94790bd6": [
      12
    ],
    "bb9e3328": [
      12
    ],
    "ce44c084": [
      12
    ],
    "08be8ff1": [
      2
    ],
    "564d4ca0": [
      12
    ],
    "e1153b12": [
      12
    ],
    "da61ad94": [
      12
    ],
    "0eb4a8b5": [
      12
    ],
    "1812584a": [
      12
    ],
    "4216fff7": [
      12
    ],
    "43352f50": [
      12
    ],
    "1349ddbb": [
      12
    ],
    "4bcb4416": [
      12
    ],
    "1629b32c": [
      12
    ],
    "3ef4a294": [
      12
    ],
    "e91f312e": [
      12
    ],
    "2dca9613": [
      12
    ],
    "7a8d9f78": [
      12
    ],
    "1a07b928": [
      12
    ],
    "10019a1e": [
      12
    ],
    "cd5626ac": [
      12
    ],
    "3e72fff0": [
      12
    ],
    "6f35a2bc": [
      12
    ],
    "18a9c86f": [
      12
    ],
    "0833fb5a": [
      12
    ],
    "2e703339": [
      12
    ],
    "6699c50b": [
      12
    ],
    "4f7f9d78": [
      12
    ],
    "1dc3c874": [
      12
    ],
    "ec68fa80": [
      12
    ],
    "251ca370": [
      12
    ],
    "6f4ef72f": [
      12
    ],
    "7d3f4270": [
      9
    ],
    "430151c6": [
      2
    ],
    "6a002c7e": [
      9
    ],
    "99edf8a2": [
      12
    ],
    "ef8c9c3a": [
      9
    ],
    "3b9b8dfe": [
      12
    ],
    "578b99d8": [
      12
    ],
    "4a125f12": [
      12
    ],
    "34ad3b47": [
      12
    ],
    "203ebaae": [
      12
    ],
    "18b9d7fe": [
      12
    ],
    "115520ca": [
      12
    ],
    "439b588b": [
      12
    ],
    "27ee2870": [
      12
    ],
    "4a494080": [
      12
    ],
    "160da3d1": [
      12
    ],
    "015570dc": [
      12
    ],
    "7acc8b28": [
      12
    ],
    "5c5078cc": [
      12
    ],
    "8acb39f6": [
      12
    ],
    "7a46a50e": [
      12
    ],
    "2602423c": [
      12
    ],
    "154f50c4": [
      12
    ],
    "7b959717": [
      12
    ],
    "4df1f9d4": [
      12
    ],
    "279299c4": [
      12
    ],
    "7285d060": [
      12
    ],
    "2152e9cb": [
      12
    ],
    "ab83f99c": [
      12
    ],
    "f653bb30": [
      12
    ],
    "f15d10e2": [
      12
    ],
    "7ecdab12": [
      12
    ],
    "4b878895": [
      12
    ],
    "8eb6b8f0": [
      12
    ],
    "134a9033": [
      12
    ],
    "5c1f15d5": [
      12
    ],
    "51ecb552": [
      12
    ],
    "37f562e0": [
      12
    ],
    "a8b6ccaa": [
      2
    ],
    "743a6b92": [
      2
    ],
    "09aba622": [
      12
    ],
    "64ad6be4": [
      9
    ],
    "72114f9e": [
      9
    ],
    "5c0b978d": [
      9
    ],
    "07695678": [
      9
    ],
    "633fcfc8": [
      9
    ],
    "d3d800ba": [
      9
    ],
    "9f261f82": [
      9
    ],
    "e06fca4c": [
      9
    ],
    "4c7f1806": [
      9
    ],
    "2fb3e4e0": [
      9
    ],
    "c2397386": [
      12
    ],
    "a8273c58": [
      9
    ],
    "321d8292": [
      2
    ],
    "b02979ba": [
      2
    ],
    "74db4977": [
      2
    ],
    "312091c6": [
      12
    ],
    "7b0cfe02": [
      12
    ],
    "4a3abd12": [
      2
    ],
    "6e3109a0": [
      9
    ],
    "166f3b78": [
      2
    ],
    "d50fd998": [
      12
    ],
    "16e56cb6": [
      12
    ],
    "6b0c37a8": [
      12
    ],
    "570567cc": [
      12
    ],
    "058dcce6": [
      12
    ],
    "34d1cba0": [
      12
    ],
    "c23772a0": [
      12
    ],
    "6a7e8112": [
      12
    ],
    "638b2d5f": [
      12
    ],
    "8aec4aea": [
      12
    ],
    "b48b3112": [
      12
    ],
    "89b36248": [
      12
    ],
    "011e5c83": [
      12
    ],
    "1bc82a1a": [
      12
    ],
    "6273baca": [
      12
    ],
    "c80d8378": [
      12
    ],
    "0384f7d5": [
      12
    ],
    "3e09fa48": [
      12
    ],
    "f3d7f0ac": [
      12
    ],
    "0f2b8bb4": [
      12
    ],
    "12e582d0": [
      12
    ],
    "71378db3": [
      12
    ],
    "69775fd0": [
      12
    ],
    "26fcc1d5": [
      12
    ],
    "11a4c342": [
      12
    ],
    "28cd26a8": [
      12
    ],
    "69db35fc": [
      12
    ],
    "6eed848e": [
      12
    ],
    "1fb7f4c5": [
      12
    ],
    "acb99476": [
      12
    ],
    "27fe9dcc": [
      12
    ],
    "5b91e2cc": [
      12
    ],
    "5845bbbf": [
      12
    ],
    "8424c514": [
      12
    ],
    "b08eaa7e": [
      12
    ],
    "1c163156": [
      12
    ],
    "6b887c23": [
      12
    ],
    "1f3dd5d6": [
      2
    ],
    "02d58e5e": [
      2
    ],
    "6523d9be": [
      2
    ],
    "14a95e2a": [
      2
    ],
    "7a5ed5ef": [
      2
    ],
    "193cda48": [
      2
    ],
    "ad0da6f6": [
      9
    ],
    "edb7729c": [
      9
    ],
    "70a2a69b": [
      12
    ],
    "08cf8db2": [
      12
    ],
    "cff18c7e": [
      12
    ],
    "e02ba6a4": [
      9
    ],
    "1b4fed42": [
      9
    ],
    "7b1c73b8": [
      9
    ],
    "65a07ade": [
      9
    ],
    "5b34225b": [
      9
    ],
    "1362dbe0": [
      9
    ],
    "00e4d01d": [
      6
    ],
    "3ea05587": [
      6
    ],
    "2ef9b060": [
      6
    ],
    "668db27f": [
      11,
      7
    ],
    "49376f32": [
      7
    ],
    "36f653bd": [
      7
    ],
    "5e89c0fc": [
      7
    ],
    "1e3bca3e": [
      7
    ],
    "52efe8be": [
      7
    ],
    "310805bc": [
      7
    ],
    "482b4e28": [
      7
    ],
    "2ae496d4": [
      7
    ],
    "36d51aa2": [
      5
    ],
    "7c439057": [
      5
    ],
    "634a7263": [
      5
    ],
    "4117f62f": [
      5
    ],
    "71ac7454": [
      5
    ],
    "19f81670": [
      8
    ],
    "373b919a": [
      8
    ],
    "cf154870": [
      8
    ],
    "2bab8a5b": [
      8
    ],
    "0b2521ed": [
      4
    ],
    "2f057c10": [
      4
    ],
    "526e7515": [
      4
    ],
    "62d77102": [
      4
    ],
    "7daa5cf0": [
      6
    ],
    "e595da52": [
      6
    ],
    "53a68402": [
      6
    ]
  },
  "assetsMapping": {
    "1a3ae26b": [
      "0d6d1e0.js"
    ],
    "6fca0322": [
      "1c89a98.js"
    ],
    "2b28186e": [
      "21b145b.js"
    ],
    "ae065404": [
      "404dfba.js"
    ],
    "51bae372": [
      "41ef2dc.js"
    ],
    "72f637b4": [
      "47366b6.js"
    ],
    "2a130dde": [
      "8cafa7b.js"
    ],
    "7ea24c87": [
      "8da1490.js"
    ],
    "be5ea2d0": [
      "bb01b66.js"
    ],
    "085a35c4": [
      "cf78498.js"
    ]
  }
}